{
  "formatVersion": 1,
  "database": {
    "version": 4,
    "identityHash": "963f3fcbbd1c9c32c33494c4559962d0",
    "entities": [
      {
        "tableName": "audit_entries",
        "createSql": "CREATE TABLE IF NOT EXISTS `${TABLE_NAME}` (`id` INTEGER PRIMARY KEY AUTOINCREMENT NOT NULL, `sessionId` TEXT NOT NULL, `toolName` TEXT NOT NULL, `provider` TEXT NOT NULL, `timestampMillis` INTEGER NOT NULL, `durationMillis` INTEGER NOT NULL, `success` INTEGER NOT NULL, `errorMessage` TEXT, `argumentsJson` TEXT, `resultJson` TEXT, `clientLabel` TEXT)",
        "fields": [
          {
            "fieldPath": "id",
            "columnName": "id",
            "affinity": "INTEGER",
            "notNull": true
          },
          {
            "fieldPath": "sessionId",
            "columnName": "sessionId",
            "affinity": "TEXT",
            "notNull": true
          },
          {
            "fieldPath": "toolName",
            "columnName": "toolName",
            "affinity": "TEXT",
            "notNull": true
          },
          {
            "fieldPath": "provider",
            "columnName": "provider",
            "affinity": "TEXT",
            "notNull": true
          },
          {
            "fieldPath": "timestampMillis",
            "columnName": "timestampMillis",
            "affinity": "INTEGER",
            "notNull": true
          },
          {
            "fieldPath": "durationMillis",
            "columnName": "durationMillis",
            "affinity": "INTEGER",
            "notNull": true
          },
          {
            "fieldPath": "success",
            "columnName": "success",
            "affinity": "INTEGER",
            "notNull": true
          },
          {
            "fieldPath": "errorMessage",
            "columnName": "errorMessage",
            "affinity": "TEXT"
          },
          {
            "fieldPath": "argumentsJson",
            "columnName": "argumentsJson",
            "affinity": "TEXT"
          },
          {
            "fieldPath": "resultJson",
            "columnName": "resultJson",
            "affinity": "TEXT"
          },
          {
            "fieldPath": "clientLabel",
            "columnName": "clientLabel",
            "affinity": "TEXT"
          }
        ],
        "primaryKey": {
          "autoGenerate": true,
          "columnNames": [
            "id"
          ]
        }
      },
      {
        "tableName": "mcp_request_entries",
        "createSql": "CREATE TABLE IF NOT EXISTS `${TABLE_NAME}` (`id` INTEGER PRIMARY KEY AUTOINCREMENT NOT NULL, `sessionId` TEXT NOT NULL, `provider` TEXT NOT NULL, `method` TEXT NOT NULL, `timestampMillis` INTEGER NOT NULL, `durationMillis` INTEGER NOT NULL, `resultBytes` INTEGER, `paramsJson` TEXT)",
        "fields": [
          {
            "fieldPath": "id",
            "columnName": "id",
            "affinity": "INTEGER",
            "notNull": true
          },
          {
            "fieldPath": "sessionId",
            "columnName": "sessionId",
            "affinity": "TEXT",
            "notNull": true
          },
          {
            "fieldPath": "provider",
            "columnName": "provider",
            "affinity": "TEXT",
            "notNull": true
          },
          {
            "fieldPath": "method",
            "columnName": "method",
            "affinity": "TEXT",
            "notNull": true
          },
          {
            "fieldPath": "timestampMillis",
            "columnName": "timestampMillis",
            "affinity": "INTEGER",
            "notNull": true
          },
          {
            "fieldPath": "durationMillis",
            "columnName": "durationMillis",
            "affinity": "INTEGER",
            "notNull": true
          },
          {
            "fieldPath": "resultBytes",
            "columnName": "resultBytes",
            "affinity": "INTEGER"
          },
          {
            "fieldPath": "paramsJson",
            "columnName": "paramsJson",
            "affinity": "TEXT"
          }
        ],
        "primaryKey": {
          "autoGenerate": true,
          "columnNames": [
            "id"
          ]
        }
      }
    ],
    "setupQueries": [
      "CREATE TABLE IF NOT EXISTS room_master_table (id INTEGER PRIMARY KEY,identity_hash TEXT)",
      "INSERT OR REPLACE INTO room_master_table (id,identity_hash) VALUES(42, '963f3fcbbd1c9c32c33494c4559962d0')"
    ]
  }
}